pyproject.toml
setup.py
../../src/add.c
../../src/alloc.c
../../src/blasphemy.c
../../src/cholesky.c
../../src/cholesky_solve.c
../../src/csc.c
../../src/csr.c
../../src/dense.c
../../src/mul.c
benchmarks/cholesky.py
benchmarks/generate_data.py
spars/__init__.py
spars/__init__.pyi
spars/_sparse_c.pyi
spars/cholesky.py
spars/csc.py
spars/csr.py
spars/lil.py
spars/py.typed
spars/spars_add.c
spars/spars_cholesky.c
spars/spars_csc.c
spars/spars_csr.c
spars/spars_module.c
spars/spars_mul.c
spars.egg-info/PKG-INFO
spars.egg-info/SOURCES.txt
spars.egg-info/dependency_links.txt
spars.egg-info/requires.txt
spars.egg-info/top_level.txt
tests/__init__.py
tests/matrices.py
tests/test_add.py
tests/test_cholesky.py
tests/test_cholesky_lsqr.py
tests/test_csc.py
tests/test_csr.py
tests/test_lil.py
tests/test_mul.py
tests/test_transpose.py