Metadata-Version: 2.4
Name: spars
Version: 0.1.2
Summary: Lightweight sparse matrix library
Author-email: Samuel Carlsson <samuel.carlsson@gmail.com>
Requires-Python: >=3.7
Requires-Dist: numpy
Provides-Extra: dev
Requires-Dist: pytest; extra == "dev"
Requires-Dist: mypy; extra == "dev"
Requires-Dist: types-setuptools; extra == "dev"
